huispedia/__init__.py
huispedia/_core.py
huispedia-0.1.0.dist-info/LICENSE
huispedia-0.1.0.dist-info/WHEEL
huispedia-0.1.0.dist-info/METADATA
huispedia-0.1.0.dist-info/RECORD
