Metadata-Version: 2.1
Name: huispedia
Version: 0.1.0
Summary: Get information about houses from huispedia.nl
Home-page: https://github.com/orsinium-labs/huispedia
License: MIT
Keywords: huispedia,nl,house,appartment
Author: Gram
Author-email: gram@orsinium.dev
Requires-Python: >=3.6
Classifier: Development Status :: 5 - Production/Stable
Classifier: Environment :: Plugins
Classifier: Intended Audience :: Developers
Classifier: License :: OSI Approved :: MIT License
Classifier: Programming Language :: Python
Classifier: Topic :: Software Development
Classifier: Topic :: Software Development :: Libraries :: Python Modules
Requires-Dist: requests
Requires-Dist: pytest ; extra == "test"
Provides-Extra: test
